flatson/__init__.py
flatson/flatson.py
flatson-0.1.0.dist-info/DESCRIPTION.rst
flatson-0.1.0.dist-info/METADATA
flatson-0.1.0.dist-info/RECORD
flatson-0.1.0.dist-info/WHEEL
flatson-0.1.0.dist-info/metadata.json
flatson-0.1.0.dist-info/top_level.txt
