Metadata-Version: 2.0
Name: flatson
Version: 0.1.0
Summary: Tool to flatten stream of JSON-like objects, configured via schema
Home-page: https://github.com/scrapinghub/flatson
Author: ScrapingHub
Author-email: info@scrapinghub.com
License: BSD
Keywords: flatson
Platform: UNKNOWN
Classifier: Development Status :: 2 - Pre-Alpha
Classifier: Intended Audience :: Developers
Classifier: License :: OSI Approved :: BSD License
Classifier: Natural Language :: English
Classifier: Programming Language :: Python :: 2
Classifier: Programming Language :: Python :: 2.6
Classifier: Programming Language :: Python :: 2.7
Classifier: Programming Language :: Python :: 3
Classifier: Programming Language :: Python :: 3.3
Classifier: Programming Language :: Python :: 3.4
